towbintools/__init__.py
towbintools/classification/__init__.py
towbintools/classification/classification_tools.py
towbintools/classification/qc_tools.py
towbintools/data_analysis/__init__.py
towbintools/data_analysis/growth_rate.py
towbintools/data_analysis/time_series.py
towbintools/deep_learning/__init__.py
towbintools/deep_learning/deep_learning_tools.py
towbintools/deep_learning/architectures/__init__.py
towbintools/deep_learning/architectures/archs.py
towbintools/deep_learning/architectures/models.py
towbintools/deep_learning/utils/__init__.py
towbintools/deep_learning/utils/augmentation.py
towbintools/deep_learning/utils/dataset.py
towbintools/deep_learning/utils/loss.py
towbintools/deep_learning/utils/util.py
towbintools/foundation/__init__.py
towbintools/foundation/binary_image.py
towbintools/foundation/detect_molts.py
towbintools/foundation/file_handling.py
towbintools/foundation/image_handling.py
towbintools/foundation/image_quality.py
towbintools/foundation/keypoint_detection.py
towbintools/foundation/utils.py
towbintools/foundation/worm_features.py
towbintools/foundation/zstack.py
towbintools/quantification/__init__.py
towbintools/quantification/quantification_tools.py
towbintools/segmentation/__init__.py
towbintools/segmentation/segmentation_tools.py
towbintools/straightening/__init__.py
towbintools/straightening/straightening_tools.py
towbintools-0.3.14.dist-info/licenses/LICENSE
towbintools-0.3.14.dist-info/METADATA
towbintools-0.3.14.dist-info/WHEEL
towbintools-0.3.14.dist-info/top_level.txt
towbintools-0.3.14.dist-info/RECORD
