Metadata-Version: 2.4
Name: towbintools
Version: 0.3.14
Summary: All the tools used by the Towbin Lab !
Author-email: Sacha Psalmon <sacha.psalmon@unibe.ch>, Boris Gusev <boris.gusev@unibe.ch>
Maintainer-email: Sacha Psalmon <sacha.psalmon@unibe.ch>
Requires-Python: >=3.8
License-File: LICENSE
Requires-Dist: torch
Requires-Dist: pytorch-lightning
Requires-Dist: torchmetrics
Requires-Dist: pytorch-toolbelt
Requires-Dist: segmentation-models-pytorch
Requires-Dist: timm
Requires-Dist: albumentations
Requires-Dist: csbdeep
Requires-Dist: scikit-learn
Requires-Dist: xgboost
Requires-Dist: joblib
Requires-Dist: opencv-contrib-python
Requires-Dist: scikit-image
Requires-Dist: tifffile
Requires-Dist: numpy
Requires-Dist: pandas
Requires-Dist: polars
Requires-Dist: pyarrow
Requires-Dist: scipy
Requires-Dist: ome-types
Requires-Dist: whittaker-eilers
Provides-Extra: dev
Requires-Dist: black; extra == "dev"
Requires-Dist: isort; extra == "dev"
Requires-Dist: pre-commit; extra == "dev"
Dynamic: license-file
